<?xml version='1.0' encoding='utf-8' standalone='yes' ?>
<map>
    <boolean name="EnableThreadedGPURes" value="true" />
    <boolean name="NeedFlushForDepthBuffer" value="false" />
    <boolean name="ForceDisableBinaryShader" value="false" />
    <boolean name="ModifyFmodDspBuffer" value="false" />
    <boolean name="EnableRenderThread" value="true" />
    <boolean name="UseShaderCache" value="false" />
    <boolean name="need_remove_shader_cache" value="false" />
    <boolean name="SupportFloatTexture" value="true" />
    <int name="RealWidth" value="960" />
    <boolean name="ForceDisableBatching" value="false" />
    <boolean name="SupportInternalBGRA" value="true" />
    <int name="Storage" value="0" />
    <int name="RealHeight" value="540" />
    <boolean name="ShadowMapDepthSameWithScreen" value="false" />
    <boolean name="EnableShadowMap" value="true" />
    <boolean name="NeedResetProgramWhenVBChange" value="false" />
    <boolean name="ForceFinishAfterUnlock" value="false" />
    <string name="NeoXRoot">/storage/emulated/0/Android/data/com.netease.onmyoji.wyzymnqsd_cps/files/netease/onmyoji</string>
    <boolean name="ForceDisableGLMap" value="false" />
    <string name="DEVICE_RELEASE">12</string>
</map>
